dcmd.py
dcmd-0.13.dist-info/METADATA
dcmd-0.13.dist-info/WHEEL
dcmd-0.13.dist-info/entry_points.txt
dcmd-0.13.dist-info/top_level.txt
dcmd-0.13.dist-info/RECORD
